setup.py
src/MotionClouds.py
src/MotionClouds.egg-info/PKG-INFO
src/MotionClouds.egg-info/SOURCES.txt
src/MotionClouds.egg-info/dependency_links.txt
src/MotionClouds.egg-info/pbr.json
src/MotionClouds.egg-info/requires.txt
src/MotionClouds.egg-info/top_level.txt