Metadata-Version: 1.1
Name: MotionClouds
Version: 0.3
Summary: Model-based stimulus synthesis of natural-like random textures for the study of motion perception.
Home-page: https://github.com/NeuralEnsemble/MotionClouds
Author: Laurent Perrinet INT - CNRS
Author-email: Laurent.Perrinet@univ-amu.fr
License: GPLv2
Download-URL: https://github.com/NeuralEnsemble/MotionClouds/tarball/0.3
Keywords: computational neuroscience,simulation,analysis,visualization,parameters
Platform: UNKNOWN
Classifier: Development Status :: 3 - Alpha
Classifier: Environment :: Console
Classifier: License :: OSI Approved :: GNU General Public License (GPL)
Classifier: Operating System :: POSIX
Classifier: Intended Audience :: Science/Research
Classifier: Topic :: Scientific/Engineering :: Visualization
Classifier: Topic :: Scientific/Engineering
Classifier: Topic :: Utilities
Classifier: Programming Language :: Python :: 2
Classifier: Programming Language :: Python :: 2.7
Classifier: Programming Language :: Python :: 3
Classifier: Programming Language :: Python :: 3.5
